commony/__init__.py
commony/crypto.py
commony/func.py
commony/misc.py
commony-0.3.0.dist-info/METADATA
commony-0.3.0.dist-info/RECORD
commony-0.3.0.dist-info/WHEEL
commony-0.3.0.dist-info/top_level.txt
